multikeyiterdict/README.MD
multikeyiterdict/__init__.py
multikeyiterdict/requirements.txt
multikeyiterdict/thirdparty.json
multikeyiterdict-0.12.dist-info/LICENSE.rst
multikeyiterdict-0.12.dist-info/METADATA
multikeyiterdict-0.12.dist-info/WHEEL
multikeyiterdict-0.12.dist-info/top_level.txt
multikeyiterdict-0.12.dist-info/RECORD
