Metadata-Version: 2.1
Name: multikeyiterdict
Version: 0.12
Summary: MultiKeyIterDict enhances the capabilities of the standard dictionary by supporting multiple keys, nested searches, and operations such as updates and merges (without loosing data) on dicts
Home-page: https://github.com/hansalemaos/multikeyiterdict
Author: Johannes Fischer
Author-email: aulasparticularesdealemaosp@gmail.com
License: MIT
Keywords: nested
Classifier: Development Status :: 4 - Beta
Classifier: Programming Language :: Python :: 3 :: Only
Classifier: Programming Language :: Python :: 3.10
Classifier: Topic :: Software Development :: Libraries :: Python Modules
Classifier: Topic :: Utilities
License-File: LICENSE.rst
